reduce_memory_usage/__init__.py
reduce_memory_usage/reduce_memory_usage.py
reduce_memory_usage-0.0.1.dist-info/LICENSE
reduce_memory_usage-0.0.1.dist-info/METADATA
reduce_memory_usage-0.0.1.dist-info/WHEEL
reduce_memory_usage-0.0.1.dist-info/top_level.txt
reduce_memory_usage-0.0.1.dist-info/RECORD
