Metadata-Version: 2.1
Name: reduce-memory-usage
Version: 0.0.1
Summary: Python scripts to reduce memory usage
Home-page: https://github.com/nakabeppu/reduce_memory_usage.git
Author: Taichi Nakabeppu
Author-email: nakabepputaichi@gmail.com
Keywords: reduce,memory
Classifier: Programming Language :: Python :: 3.7
Classifier: License :: OSI Approved :: MIT License
Classifier: Operating System :: OS Independent
License-File: LICENSE
